CHANGES.txt
LICENSE.txt
MANIFEST.in
README.md
setup.cfg
setup.py
labview_automation/__init__.py
labview_automation/client.py
labview_automation/labview.py
labview_automation/labview.py.bak
labview_automation.egg-info/PKG-INFO
labview_automation.egg-info/SOURCES.txt
labview_automation.egg-info/dependency_links.txt
labview_automation.egg-info/requires.txt
labview_automation.egg-info/top_level.txt
labview_automation/__pycache__/__init__.cpython-37.pyc
labview_automation/__pycache__/client.cpython-37.pyc
labview_automation/__pycache__/labview.cpython-37.pyc
lv_listener/BSON/BSON.lvlib
lv_listener/BSON/BSONObjectProbe.vi
lv_listener/BSON/I32toByteArray.vi
lv_listener/BSON/_errorHandler.vi
lv_listener/BSON/byteArrayToI32.vi
lv_listener/BSON/byteArrayToString.vi
lv_listener/BSON/status.ctl
lv_listener/BSON/stringToByteArray.vi
lv_listener/BSON/toSlashCodeString.vi
lv_listener/BSON/BSONElements/tBSONArray/decodeStream.vi
lv_listener/BSON/BSONElements/tBSONArray/encodeStream.vi
lv_listener/BSON/BSONElements/tBSONArray/getType.vi
lv_listener/BSON/BSONElements/tBSONArray/getValue.vi
lv_listener/BSON/BSONElements/tBSONArray/setValue.vi
lv_listener/BSON/BSONElements/tBSONArray/tBSONArray.lvclass
lv_listener/BSON/BSONElements/tBSONArray/toJSON.vi
lv_listener/BSON/BSONElements/tBSONBinary/Subtype.ctl
lv_listener/BSON/BSONElements/tBSONBinary/decodeStream.vi
lv_listener/BSON/BSONElements/tBSONBinary/encodeStream.vi
lv_listener/BSON/BSONElements/tBSONBinary/getSubtype.vi
lv_listener/BSON/BSONElements/tBSONBinary/getType.vi
lv_listener/BSON/BSONElements/tBSONBinary/getValue.vi
lv_listener/BSON/BSONElements/tBSONBinary/setSubtype.vi
lv_listener/BSON/BSONElements/tBSONBinary/setValue.vi
lv_listener/BSON/BSONElements/tBSONBinary/tBSONBinary.lvclass
lv_listener/BSON/BSONElements/tBSONBinary/toJSON.vi
lv_listener/BSON/BSONElements/tBSONBoolean/decodeStream.vi
lv_listener/BSON/BSONElements/tBSONBoolean/encodeStream.vi
lv_listener/BSON/BSONElements/tBSONBoolean/getType.vi
lv_listener/BSON/BSONElements/tBSONBoolean/getValue.vi
lv_listener/BSON/BSONElements/tBSONBoolean/setValue.vi
lv_listener/BSON/BSONElements/tBSONBoolean/tBSONBoolean.lvclass
lv_listener/BSON/BSONElements/tBSONBoolean/toJSON.vi
