Metadata-Version: 1.1
Name: labview-automation
Version: 15.0.0.dev23
Summary: Tools for working with LabVIEW
Home-page: UNKNOWN
Author: UNKNOWN
Author-email: UNKNOWN
License: MIT
Download-URL: https://gitlab.com/croningroup/chemputer/python_labview_automation/-/archive/v0.1.0/python_labview_automation-v0.1.0.tar.gz
Platform: UNKNOWN
